[
  {
    "title": "Curso HELVIA - IES Gonzalo Nazareno (2007)",
    "children": [
      {
        "title": "Introducción",
        "url": "/cursos/helvia2007/index.html#introducción"
      },
      {
        "title": "Uso de la plataforma como usuario",
        "url": "/cursos/helvia2007/index.html#uso-de-la-plataforma-como-usuario"
      },
      {
        "title": "Prácticas",
        "url": "/cursos/helvia2007/index.html#prácticas"
      },
      {
        "title": "Encuestas",
        "url": "/cursos/helvia2007/index.html#encuestas"
      },
      {
        "title": "Uso de la plataforma como administrador",
        "url": "/cursos/helvia2007/index.html#uso-de-la-plataforma-como-administrador"
      },
      {
        "title": "Prácticas",
        "url": "/cursos/helvia2007/index.html#prácticas-1"
      },
      {
        "title": "Trabajo no presencial",
        "url": "/cursos/helvia2007/index.html#trabajo-no-presencial"
      },
      {
        "title": "Recursos",
        "url": "/cursos/helvia2007/index.html#recursos"
      }
    ]
  }
]